biometal.libs/libcrypto-c19c2cf8.so.3
biometal.libs/libssl-63597a81.so.3
biometal/__init__.py
biometal/biometal.cpython-311-x86_64-linux-gnu.so
biometal_rs-1.3.0.dist-info/METADATA
biometal_rs-1.3.0.dist-info/WHEEL
biometal_rs-1.3.0.dist-info/licenses/LICENSE-APACHE
biometal_rs-1.3.0.dist-info/licenses/LICENSE-MIT
biometal_rs-1.3.0.dist-info/RECORD
