Metadata-Version: 2.4
Name: biometal-rs
Version: 1.3.0
Classifier: Development Status :: 5 - Production/Stable
Classifier: Intended Audience :: Science/Research
Classifier: License :: OSI Approved :: MIT License
Classifier: License :: OSI Approved :: Apache Software License
Classifier: Programming Language :: Python :: 3
Classifier: Programming Language :: Python :: 3.9
Classifier: Programming Language :: Python :: 3.10
Classifier: Programming Language :: Python :: 3.11
Classifier: Programming Language :: Python :: 3.12
Classifier: Programming Language :: Python :: 3.13
Classifier: Programming Language :: Python :: 3.14
Classifier: Programming Language :: Rust
Classifier: Topic :: Scientific/Engineering :: Bio-Informatics
License-File: LICENSE-APACHE
License-File: LICENSE-MIT
Summary: ARM-native bioinformatics library with streaming architecture and evidence-based optimization
Keywords: bioinformatics,genomics,arm,neon,streaming
Home-Page: https://github.com/shandley/biometal
Author-email: Scott Handley <scott.handley@example.com>
License: MIT OR Apache-2.0
Requires-Python: >=3.9
Project-URL: Homepage, https://github.com/shandley/biometal
Project-URL: Documentation, https://docs.rs/biometal
Project-URL: Repository, https://github.com/shandley/biometal
